pymdfu/__init__.py
pymdfu/logfilters.py
pymdfu/logging.toml
pymdfu/mdfu.py
pymdfu/pymdfu.py
pymdfu/pymdfuclient.py
pymdfu/pymdfuclient_cli.py
pymdfu/status_codes.py
pymdfu/timeout.py
pymdfu/utils.py
pymdfu/drivers/mcp2221a.py
pymdfu/mac/__init__.py
pymdfu/mac/aardvark_mac.py
pymdfu/mac/bytes_mac.py
pymdfu/mac/exceptions.py
pymdfu/mac/linux_i2c_mac.py
pymdfu/mac/linux_spi_mac.py
pymdfu/mac/mac.py
pymdfu/mac/mcp2210_mac.py
pymdfu/mac/mcp2221a_mac.py
pymdfu/mac/network_mac.py
pymdfu/mac/packet_mac.py
pymdfu/mac/serial_mac.py
pymdfu/tools/__init__.py
pymdfu/tools/aardvark.py
pymdfu/tools/linux_i2c.py
pymdfu/tools/linux_spi.py
pymdfu/tools/mcp2210.py
pymdfu/tools/mcp2221a.py
pymdfu/tools/nedbg.py
pymdfu/tools/network.py
pymdfu/tools/python_can.py
pymdfu/tools/python_can_tp.py
pymdfu/tools/serial_generic.py
pymdfu/tools/simulator.py
pymdfu/tools/tools.py
pymdfu/transport/__init__.py
pymdfu/transport/i2c_transport.py
pymdfu/transport/spi_transport.py
pymdfu/transport/uart_transport.py
pymdfu-2.7.0.12.dist-info/licenses/LICENSE.txt
pymdfu-2.7.0.12.dist-info/METADATA
pymdfu-2.7.0.12.dist-info/WHEEL
pymdfu-2.7.0.12.dist-info/entry_points.txt
pymdfu-2.7.0.12.dist-info/top_level.txt
pymdfu-2.7.0.12.dist-info/RECORD
